nixtract/__init__.py
nixtract/cli/__init__.py
nixtract/cli/base.py
nixtract/cli/cifti.py
nixtract/cli/gifti.py
nixtract/cli/nifti.py
nixtract/extractors/__init__.py
nixtract/extractors/base_extractor.py
nixtract/extractors/cifti_extractor.py
nixtract/extractors/gifti_extractor.py
nixtract/extractors/nifti_extractor.py
nixtract/extractors/utils.py
nixtract-0.0.2.dist-info/LICENSE
nixtract-0.0.2.dist-info/METADATA
nixtract-0.0.2.dist-info/WHEEL
nixtract-0.0.2.dist-info/entry_points.txt
nixtract-0.0.2.dist-info/top_level.txt
nixtract-0.0.2.dist-info/RECORD
