Metadata-Version: 2.1
Name: nixtract
Version: 0.0.2
Summary: A unified interface for timeseries extraction from different functional neuroimaging file types
Home-page: https://github.com/danjgale/nixtract
Author: Dan Gale
Maintainer-email: d.gale@queensu.ca
License: MIT
Platform: UNKNOWN
Classifier: Programming Language :: Python :: 3
Classifier: Operating System :: OS Independent
Classifier: Intended Audience :: Science/Research
Classifier: Intended Audience :: Developers
Classifier: Topic :: Scientific/Engineering
Requires-Python: >=3.6.0
Requires-Dist: numpy (>=1.16.5)
Requires-Dist: pandas (>=1.1.0)
Requires-Dist: nibabel (>=3.2.0)
Requires-Dist: nilearn (>=0.7.1)
Requires-Dist: natsort (>=7.1.1)
Requires-Dist: scipy (>=1.5.0)
Requires-Dist: scikit-learn (>=0.24.1)
Requires-Dist: load-confounds (>=0.11.1)
Provides-Extra: test
Requires-Dist: pytest-cov ; extra == 'test'
Requires-Dist: pytest ; extra == 'test'
